LICENSE
repltalk/__init__.py
repltalk/graphql.py
repltalk/queries.py
repltalk-1.0.1.dist-info/LICENSE
repltalk-1.0.1.dist-info/WHEEL
repltalk-1.0.1.dist-info/METADATA
repltalk-1.0.1.dist-info/RECORD
