Metadata-Version: 2.1
Name: repltalk
Version: 1.0.1
Summary: Allows you to do various things with the kind of unofficial Replit Repl Talk API
Home-page: https://github.com/mat-1/repl-talk-api
License: MIT
Author: mat
Author-email: pypirepltalk@matdoes.dev
Requires-Python: >=3.8,<4.0
Classifier: License :: OSI Approved :: MIT License
Classifier: Programming Language :: Python :: 3
Classifier: Programming Language :: Python :: 3.8
Classifier: Programming Language :: Python :: 3.9
Requires-Dist: aiohttp (>=3.6,<4.0)
Project-URL: Repository, https://github.com/mat-1/repl-talk-api
